zax/__init__.py
zax/__main__.py
zax/common.py
zax/config.py
zax/formats/__init__.py
zax/formats/ddraw.ini.yml
zax/formats/f2_res.ini.yml
zax/formats/fallout2.cfg.yml
zax/games.py
zax/icons/__init__.py
zax/icons/fallout2.png
zax/icons/fallout2rpu.png
zax/icons/fallout2upu.png
zax/image_listbox.py
zax/images/splash.png
zax/images/zax.ico
zax/images/zax_png.py
zax/layout.py
zax/layouts/common.py
zax/layouts/ddraw_ini.py
zax/layouts/f2_res_ini.py
zax/layouts/fallout2_cfg.py
zax/layouts/trouble.py
zax/layouts/wine.py
zax/layouts/zax.py
zax/pyqt_hacks.py
zax/resources.py
zax/sfall.py
zax/theme.py
zax/updates.py
zax/variables.py
zax/version.py
zax/zax.spec
zax/zax_config.py
zax/zax_log.py
zax-0.7.dist-info/METADATA
zax-0.7.dist-info/WHEEL
zax-0.7.dist-info/entry_points.txt
zax-0.7.dist-info/RECORD
