Metadata-Version: 2.1
Name: zax
Version: 0.7
Summary: ZAX
Home-page: https://github.com/BGforgeNet/zax
Keywords: fallout,fallout2
Author: BGforge
Author-email: dev@bgforge.net
Requires-Python: >=3.8,<3.11
Classifier: Programming Language :: Python :: 3
Classifier: Programming Language :: Python :: 3.8
Classifier: Programming Language :: Python :: 3.9
Classifier: Programming Language :: Python :: 3.10
Requires-Dist: PySimpleGUIQt (>=0.35.0,<5)
Requires-Dist: appdirs (>=1.4.3)
Requires-Dist: cssutils (>=2.3.0)
Requires-Dist: iniparse (>=0.5)
Requires-Dist: loguru (>=0.5.3)
Requires-Dist: packaging (>=20.4)
Requires-Dist: pefile (>=2021.9.3)
Requires-Dist: py7zr (>=0.16.3)
Requires-Dist: requests (>=2.22.0)
Requires-Dist: ruamel.yaml (>=0.16.10)
Project-URL: Repository, https://github.com/BGforgeNet/zax
